[
  {
    "videoId": "tTw1z10yMCI",
    "title": "MCP Servers Explained in 5 Minutes (for beginners)",
    "descriptionSnippet": "subscribe for more ▻ https://bit.ly/3zlUmiS follow techsnif for tech news (x) ▻ https://twitter.com/techsnif follow me on twitter (x) ...",
    "channelId": "UCJFMlSxcvlZg5yZUYJT0Pug",
    "channelTitle": "corbin",
    "publishedAt": "2025-04-06T15:01:11Z"
  },
  {
    "videoId": "eur8dUO9mvE",
    "title": "What is MCP? Integrate AI Agents with Databases &amp; APIs",
    "descriptionSnippet": "Ready to become a certified Architect on Cloud Pak? Register now and use code IBMTechYT20 for 20% off of your exam ...",
    "channelId": "UCKWaEZ-_VweaEx1j62do_vQ",
    "channelTitle": "IBM Technology",
    "publishedAt": "2025-02-19T12:00:59Z"
  },
  {
    "videoId": "xdMVgZfZ1yg",
    "title": "What is MCP? Why is everyone talking about it?",
    "descriptionSnippet": "Try Zapier MCP for free today: https://bit.ly/42Babll And check out their webinar tomorrow at 10am PST: https://bit.ly/4jEZR1x Join ...",
    "channelId": "UCawZsQWqfGSbCI5yjkdVkTA",
    "channelTitle": "Matthew Berman",
    "publishedAt": "2025-05-06T22:55:40Z"
  }
]
